LICENSE
README.md
setup.py
linktree61a/__init__.py
linktree61a.egg-info/PKG-INFO
linktree61a.egg-info/SOURCES.txt
linktree61a.egg-info/dependency_links.txt
linktree61a.egg-info/top_level.txt